Metadata-Version: 2.1
Name: subjugate
Version: 1.0.0
Summary: Write templates in Django with Dominate
Home-page: https://github.com/estheruary/subjugate
Author: Estelle Poulin
Author-email: dev@inspiredby.es
License: LGPLv3
Project-URL: Source, https://github.com/estheruary/subjugate
Project-URL: Changelog, https://github.com/estheruary/subjugate/blob/main/CHANGELOG.md
Requires-Python: >=3.6
License-File: LICENSE.txt
